SpringBootKuangjiaRumenjiaochengCYuyanBianchengWangFix1/README.md
SpringBootKuangjiaRumenjiaochengCYuyanBianchengWangFix1/__init__.py
SpringBootKuangjiaRumenjiaochengCYuyanBianchengWangFix1/__main__.py
SpringBootKuangjiaRumenjiaochengCYuyanBianchengWangFix1/file.epub
SpringBootKuangjiaRumenjiaochengCYuyanBianchengWangFix1/index.html
SpringBootKuangjiaRumenjiaochengCYuyanBianchengWangFix1/css/__init__.py
SpringBootKuangjiaRumenjiaochengCYuyanBianchengWangFix1/css/annotations.css
SpringBootKuangjiaRumenjiaochengCYuyanBianchengWangFix1/css/main.css
SpringBootKuangjiaRumenjiaochengCYuyanBianchengWangFix1/css/normalize.css
SpringBootKuangjiaRumenjiaochengCYuyanBianchengWangFix1/css/popup.css
SpringBootKuangjiaRumenjiaochengCYuyanBianchengWangFix1/font/__init__.py
SpringBootKuangjiaRumenjiaochengCYuyanBianchengWangFix1/font/fontello.eot
SpringBootKuangjiaRumenjiaochengCYuyanBianchengWangFix1/font/fontello.svg
SpringBootKuangjiaRumenjiaochengCYuyanBianchengWangFix1/font/fontello.ttf
SpringBootKuangjiaRumenjiaochengCYuyanBianchengWangFix1/font/fontello.woff
SpringBootKuangjiaRumenjiaochengCYuyanBianchengWangFix1/img/__init__.py
SpringBootKuangjiaRumenjiaochengCYuyanBianchengWangFix1/img/annotator-glyph-sprite.png
SpringBootKuangjiaRumenjiaochengCYuyanBianchengWangFix1/img/annotator-icon-sprite.png
SpringBootKuangjiaRumenjiaochengCYuyanBianchengWangFix1/img/apple-touch-icon.png
SpringBootKuangjiaRumenjiaochengCYuyanBianchengWangFix1/img/cancelfullscreen.png
SpringBootKuangjiaRumenjiaochengCYuyanBianchengWangFix1/img/close.png
SpringBootKuangjiaRumenjiaochengCYuyanBianchengWangFix1/img/fullscreen.png
SpringBootKuangjiaRumenjiaochengCYuyanBianchengWangFix1/img/loader.gif
SpringBootKuangjiaRumenjiaochengCYuyanBianchengWangFix1/img/menu-icon.png
SpringBootKuangjiaRumenjiaochengCYuyanBianchengWangFix1/img/save.png
SpringBootKuangjiaRumenjiaochengCYuyanBianchengWangFix1/img/saved.png
SpringBootKuangjiaRumenjiaochengCYuyanBianchengWangFix1/img/settings-s.png
spring_boot_kuangjia_rumenjiaocheng_c_yuyan_biancheng_wang_fix1-2025.3.24.0.dist-info/METADATA
spring_boot_kuangjia_rumenjiaocheng_c_yuyan_biancheng_wang_fix1-2025.3.24.0.dist-info/WHEEL
spring_boot_kuangjia_rumenjiaocheng_c_yuyan_biancheng_wang_fix1-2025.3.24.0.dist-info/entry_points.txt
spring_boot_kuangjia_rumenjiaocheng_c_yuyan_biancheng_wang_fix1-2025.3.24.0.dist-info/top_level.txt
spring_boot_kuangjia_rumenjiaocheng_c_yuyan_biancheng_wang_fix1-2025.3.24.0.dist-info/RECORD
